msfootprint/Java17.md
msfootprint/__init__.py
msfootprint/data/us_boundary.gpkg
msfootprint/find_footprinttable.py
msfootprint/globalgooglemicrosoftBF.py
msfootprint/utils.py
msfootprint-0.1.31.dist-info/METADATA
msfootprint-0.1.31.dist-info/WHEEL
msfootprint-0.1.31.dist-info/RECORD
