Metadata-Version: 2.4
Name: msfootprint
Version: 0.1.31
Summary: A tool to extract the microsoft building footprints with user defined boundary.
Author: supathdhitalGEO
Author-email: sdhital@crimson.ua.edu
Requires-Python: >=3.10,<4.0
Classifier: Programming Language :: Python :: 3
Classifier: Programming Language :: Python :: 3.10
Classifier: Programming Language :: Python :: 3.11
Classifier: Programming Language :: Python :: 3.12
Classifier: Programming Language :: Python :: 3.13
Classifier: Programming Language :: Python :: 3.14
Requires-Dist: fiona (>=1.10.1,<2.0.0)
Requires-Dist: geemap (>=0.35.3,<0.36.0)
Requires-Dist: geopandas (>=1.0.1,<2.0.0)
Requires-Dist: pyspark (==4.0.1)
Requires-Dist: pytest (>=8.3.4,<9.0.0)
Requires-Dist: setuptools
Project-URL: Repository, https://github.com/supathdhitalGEO/msfootprint
